{
  "project_info": {
    "project_number": "41464777064",
    "project_id": "oceaniccare-cb3af",
    "storage_bucket": "oceaniccare-cb3af.appspot.com"
  },
  "client": [
    {
      "client_info": {
        "mobilesdk_app_id": "1:41464777064:android:3d118e0caf90c2d937eedd",
        "android_client_info": {
          "package_name": "com.example.project_app"
        }
      },
      "oauth_client": [],
      "api_key": [
        {
          "current_key": "AIzaSyBO8lAoNGi2cQkKRWVc4N7QWi_yNEFkcys"
        }
      ],
      "services": {
        "appinvite_service": {
          "other_platform_oauth_client": []
        }
      }
    }
  ],
  "configuration_version": "1"
}